whitebox_plugin_pannellum/pyproject.toml
whitebox_plugin_pannellum/__init__.py
whitebox_plugin_pannellum/external-asset-manifest.json
whitebox_plugin_pannellum/jsx/Pannellum360Video.jsx
whitebox_plugin_pannellum/whitebox_plugin_pannellum.py
whitebox_test_plugin_pannellum/__init__.py
whitebox_test_plugin_pannellum/test_whitebox_plugin_pannellum.py
whitebox_plugin_pannellum-0.1.4.dist-info/LICENSE
whitebox_plugin_pannellum-0.1.4.dist-info/METADATA
whitebox_plugin_pannellum-0.1.4.dist-info/WHEEL
whitebox_plugin_pannellum-0.1.4.dist-info/RECORD
