Metadata-Version: 2.3
Name: whitebox-plugin-pannellum
Version: 0.1.4
Summary: Pannellum 360 video player integration
License: GNU Affero General Public License v3
Author: avilabss
Author-email: contact@avilabs.net
Requires-Python: >=3.10.0
Classifier: License :: Other/Proprietary License
Classifier: Programming Language :: Python :: 3
Classifier: Programming Language :: Python :: 3.10
Classifier: Programming Language :: Python :: 3.11
Classifier: Programming Language :: Python :: 3.12
Classifier: Programming Language :: Python :: 3.13
